CHANGES.txt
MANIFEST.in
README.md
setup.py
tao1/__init__.py
tao1.egg-info/PKG-INFO
tao1.egg-info/SOURCES.txt
tao1.egg-info/dependency_links.txt
tao1.egg-info/requires.txt
tao1.egg-info/top_level.txt
tao1/core/__init__.py
tao1/core/autoreload.py
tao1/core/core.py
tao1/core/lang.py
tao1/core/set.py
tao1/core/union.py
tao1/core/utils.py
tao1/core/utils_.py
tao1/libs/__init__.py
tao1/libs/admin/__init__.py
tao1/libs/admin/admin.py
tao1/libs/admin/routes.py
tao1/libs/admin/locale/_.pot
tao1/libs/admin/locale/en/LC_MESSAGES/_.mo
tao1/libs/admin/locale/en/LC_MESSAGES/_.po
tao1/libs/admin/locale/ru/LC_MESSAGES/_.mo
tao1/libs/admin/locale/ru/LC_MESSAGES/_.po
tao1/libs/admin/st/backbone.js
tao1/libs/admin/st/color.css
tao1/libs/admin/st/conf_templ.js
tao1/libs/admin/st/jquery.datetimepicker.js
tao1/libs/admin/st/jquery.scrollTo-min.js
tao1/libs/admin/st/json2.js
tao1/libs/admin/st/underscore.js
tao1/libs/admin/st/chosen/chosen-sprite.png
tao1/libs/admin/st/chosen/chosen.css
tao1/libs/admin/st/chosen/chosen.jquery.js
tao1/libs/admin/st/chosen/chosen.jquery.min.js
tao1/libs/admin/st/chosen/chosen.proto.js
tao1/libs/admin/st/chosen/chosen.proto.min.js
tao1/libs/admin/st/code_mirror/codemirror.js
tao1/libs/admin/st/code_mirror/keymap/emacs.js
tao1/libs/admin/st/code_mirror/keymap/vim.js
tao1/libs/admin/st/code_mirror/lib/codemirror.css
tao1/libs/admin/st/code_mirror/lib/codemirror.js
tao1/libs/admin/st/code_mirror/mode/clike/clike.js
tao1/libs/admin/st/code_mirror/mode/clike/index.html
tao1/libs/admin/st/code_mirror/mode/clike/scala.html
tao1/libs/admin/st/code_mirror/mode/clojure/clojure.js
tao1/libs/admin/st/code_mirror/mode/clojure/index.html
tao1/libs/admin/st/code_mirror/mode/coffeescript/LICENSE
tao1/libs/admin/st/code_mirror/mode/coffeescript/coffeescript.js
tao1/libs/admin/st/code_mirror/mode/coffeescript/index.html
tao1/libs/admin/st/code_mirror/mode/css/css.js
tao1/libs/admin/st/code_mirror/mode/css/index.html
tao1/libs/admin/st/code_mirror/mode/diff/diff.js
tao1/libs/admin/st/code_mirror/mode/diff/index.html
tao1/libs/admin/st/code_mirror/mode/ecl/ecl.js
tao1/libs/admin/st/code_mirror/mode/ecl/index.html
