Metadata-Version: 1.1
Name: tao1
Version: 0.2.5
Summary: framework, CMS and CRM for aiohttp and asyncio
Home-page: https://github.com/alikzao/tao
Author: Alexandre Z
Author-email: alikzao@gmail.com
License: MIT
Platform: UNKNOWN
Classifier: Intended Audience :: Developers
Classifier: Programming Language :: Python
Classifier: Programming Language :: Python :: 3.5
Classifier: Topic :: Internet :: WWW/HTTP
